bestdist/__init__.py
bestdist/core/__init__.py
bestdist/core/base.py
bestdist/core/base_discrete.py
bestdist/core/fitter.py
bestdist/distributions/__init__.py
bestdist/distributions/continuous/__init__.py
bestdist/distributions/continuous/beta.py
bestdist/distributions/continuous/cauchy.py
bestdist/distributions/continuous/exponential.py
bestdist/distributions/continuous/gamma.py
bestdist/distributions/continuous/lognormal.py
bestdist/distributions/continuous/normal.py
bestdist/distributions/continuous/student_t.py
bestdist/distributions/continuous/uniform.py
bestdist/distributions/continuous/weibull.py
bestdist/distributions/discrete/__init__.py
bestdist/distributions/discrete/binomial.py
bestdist/distributions/discrete/geometric.py
bestdist/distributions/discrete/negative_binomial.py
bestdist/distributions/discrete/poisson.py
bestdist/utils/__init__.py
bestdist/utils/exceptions.py
bestdist/utils/types.py
bestdist-0.1.1.dist-info/licenses/LICENSE
bestdist-0.1.1.dist-info/METADATA
bestdist-0.1.1.dist-info/WHEEL
bestdist-0.1.1.dist-info/top_level.txt
bestdist-0.1.1.dist-info/RECORD
